MANIFEST.in
README.md
setup.cfg
setup.py
src/shopyo_demo/__init__.py
src/shopyo_demo/forms.py
src/shopyo_demo/global.py
src/shopyo_demo/info.json
src/shopyo_demo/models.py
src/shopyo_demo/view.py
src/shopyo_demo.egg-info/PKG-INFO
src/shopyo_demo.egg-info/SOURCES.txt
src/shopyo_demo.egg-info/dependency_links.txt
src/shopyo_demo.egg-info/requires.txt
src/shopyo_demo.egg-info/top_level.txt
src/shopyo_demo/__pycache__/__init__.cpython-310.pyc
src/shopyo_demo/__pycache__/__init__.cpython-39.pyc
src/shopyo_demo/__pycache__/global.cpython-310.pyc
src/shopyo_demo/__pycache__/global.cpython-39.pyc
src/shopyo_demo/__pycache__/models.cpython-39.pyc
src/shopyo_demo/__pycache__/view.cpython-310.pyc
src/shopyo_demo/__pycache__/view.cpython-39.pyc
src/shopyo_demo/templates/status/dashboard.html
src/shopyo_demo/templates/status/blocks/sidebar.html
src/shopyo_demo/tests/test_status_functional.py
src/shopyo_demo/tests/test_status_models.py